Workbook
Name Income_List: List!$I$1:$I$10
Name Outcome_List: List!$G$1:$G$12

Sheet Money_tracker
A1: TRANSACTIONS TABLE
A2: No | B2: Date | C2: Jenis | D2: Metode Pembayaran | E2: Kategori | F2: Mata uang | G2: Keterangan | H2: Jumlah | K2: Total Pengeluaran | N2: Total Pemasukan
A3: 1 | B3: 46055 | C3: Outcome | D3: Seabank | E3: Fashion | F3: IDR | G3: Potong rambut | H3: 40000 | K3: USD | L3: IDR | N3: USD | O3: IDR
A4: 2 | C4: Outcome | D4: Seabank | E4: Makan | F4: IDR | G4: Roti dan susu | H4: 42900 | K4: =SUMIFS($H$2:$H$1000,$C$2:$C$1000,"Outcome",$F$2:$F$1000,"USD") -SUMIFS($H$2:$H$1000,$C$2:$C$1000,"Outcome",$F$2:$F$1000,"USD",$G$2:$G$1000,"*Konversi*") -SUMIFS($H$2:$H$1000,$C$2:$C$1000,"Outcome",$F$2:$F$1000,"USD",$E$2:$E$1000,"Pindah uang") -SUMIFS($H$2:$H$1000,$C$2:$C$1000,"Outcome",$F$2:$F$1000,"USD",$E$2:$E$1000,"Investasi") -> 357 | L4: =SUMIFS($H$2:$H$1000,$C$2:$C$1000,"Outcome",$F$2:$F$1000,"IDR") -SUMIFS($H$2:$H$1000,$C$2:$C$1000,"Outcome",$F$2:$F$1000,"IDR",$G$2:$G$1000,"*Konversi*") -SUMIFS($H$2:$H$1000,$C$2:$C$1000,"Outcome",$F$2:$F$1000,"IDR",$E$2:$E$1000,"Pindah uang") -SUMIFS($H$2:$H$1000,$C$2:$C$1000,"Outcome",$F$2:$F$1000,"IDR",$E$2:$E$1000,"Investasi") -> 3426670 | N4: =SUMIFS($H$2:$H$1000,$C$2:$C$1000,"Income",$F$2:$F$1000,"USD",$E$2:$E$1000,"<>Sisa") -SUMIFS($H$2:$H$1000,$C$2:$C$1000,"Income",$F$2:$F$1000,"USD",$G$2:$G$1000,"*Konversi*") -SUMIFS($H$2:$H$1000,$C$2:$C$1000,"Income",$F$2:$F$1000,"USD",$E$2:$E$1000,"Pindah uang") -> 912 | O4: =SUMIFS($H$2:$H$1000,$C$2:$C$1000,"Income",$F$2:$F$1000,"IDR",$E$2:$E$1000,"<>Sisa") -SUMIFS($H$2:$H$1000,$C$2:$C$1000,"Income",$F$2:$F$1000,"IDR",$G$2:$G$1000,"*Konversi*") -SUMIFS($H$2:$H$1000,$C$2:$C$1000,"Income",$F$2:$F$1000,"IDR",$E$2:$E$1000,"Pindah uang") -> 5055339
A5: 3 | B5: 46056 | C5: Income | D5: Jenius | E5: Gaji | F5: USD | G5: Gaji, bonus | H5: 912
A6: 5 | C6: Outcome | D6: Jenius | E6: Makan | F6: USD | G6: Uang makan | H6: 57
A7: 6 | C7: Sisa saldo | D7: Seabank | E7: Sisa saldo | F7: IDR | G7: Sisa saldo | H7: =1594000+82900 -> 1676900
A8: 7 | C8: Sisa saldo | D8: BCA | E8: Sisa saldo | F8: IDR | G8: Sisa saldo | H8: 192698
A9: 8 | C9: Sisa saldo | D9: Jenius | E9: Sisa saldo | F9: USD | G9: Sisa saldo | H9: 150
A10: 9 | C10: Sisa saldo | D10: BCA Vallas | E10: Sisa saldo | F10: USD | G10: Sisa saldo | H10: 5
A11: 10 | C11: Sisa saldo | D11: Investasi | E11: Sisa saldo | F11: IDR | G11: Emas | H11: =3*Rasio!G2 -> 7980000
A12: 11 | C12: Sisa saldo | D12: Investasi | E12: Sisa saldo | F12: IDR | G12: Saham | H12: 2000000
A13: 12 | B13: 46057 | C13: Pindah | D13: Jenius | E13: Transfer | F13: USD | G13: Konversi USD | H13: 300
A14: 13 | C14: Pindah | D14: Seabank | E14: Transfer | F14: IDR | G14: Konversi USD | H14: 5022739
A15: 14 | C15: Outcome | D15: Seabank | E15: Sedekah | F15: IDR | G15: Ibu | H15: 2000000
A16: 15 | C16: Outcome | D16: Seabank | E16: Rokok | F16: IDR | G16: Coil vape | H16: 66000 | K16: =H7+H18+H14 -> 7754639
A17: 16 | C17: Outcome | D17: Seabank | E17: Other | F17: IDR | G17: Tumbler | H17: 212320 | K17: =K16-(H15+H3+H4+H16+H17+H21+H18) -> 4306419
A18: 17 | C18: Pindah | D18: Seabank | E18: Transfer | F18: IDR | G18: Asuransi | H18: =705000+350000 -> 1055000
A19: 18 | C19: Income | D19: Mandiri | E19: Other | F19: IDR | G19: Asuransi | H19: 1055000
A20: 19 | C20: Outcome | D20: Mandiri | E20: Kesehatan | F20: IDR | G20: Asuransi | H20: =707200+326250 -> 1033450 | K20: =K17-3252019 -> 1054400
A21: 20 | B21: 46058 | C21: Outcome | D21: Seabank | E21: Makan | F21: IDR | G21: Tahu susu | H21: 32000
A22: 21 | C22: Income | D22: Seabank | E22: Other | F22: IDR | G22: Balancing | H22: 4000339
A23: 22 | C23: Outcome | D23: Jenius | E23: Other | F23: USD | G23: Balancing | H23: 300
A24: 23
A25: 24
A26: 25
A27: 26
A28: 27
A29: 28
A30: 29
A31: 30
A32: 31
A33: 32
A34: Jumlah

Sheet Rasio
A1: IDR ASSETS | E1: RATE | F1: KURS | G1: 16650
A2: Item | B2: IDR | C2: Presentase | F2: GOLD | G2: 2660000
A3: BCA | B3: =SUMIFS(Money_tracker!$H:$H,Money_tracker!$D:$D,$A3,Money_tracker!$C:$C,"Income",Money_tracker!$F:$F,"IDR",Money_tracker!$C:$C,"<>Pindah",Money_tracker!$E:$E,"<>Transfer",Money_tracker!$C:$C,"<>Sisa saldo")+SUMIFS(Money_tracker!$H:$H,Money_tracker!$D:$D,$A3,Money_tracker!$C:$C,"Sisa saldo",Money_tracker!$F:$F,"IDR",Money_tracker!$E:$E,"Sisa saldo")-SUMIFS(Money_tracker!$H:$H,Money_tracker!$D:$D,$A3,Money_tracker!$C:$C,"Outcome",Money_tracker!$F:$F,"IDR",Money_tracker!$C:$C,"<>Pindah",Money_tracker!$E:$E,"<>Transfer") -> 192698 | E3: Total Assets | G3: =B7+(G1*B13)+B19 -> 25299767
A4: Cash | B4: =SUMIFS(Money_tracker!$H:$H,Money_tracker!$D:$D,$A4,Money_tracker!$C:$C,"Income",Money_tracker!$F:$F,"IDR",Money_tracker!$C:$C,"<>Pindah",Money_tracker!$E:$E,"<>Transfer",Money_tracker!$C:$C,"<>Sisa saldo")+SUMIFS(Money_tracker!$H:$H,Money_tracker!$D:$D,$A4,Money_tracker!$C:$C,"Sisa saldo",Money_tracker!$F:$F,"IDR",Money_tracker!$E:$E,"Sisa saldo")-SUMIFS(Money_tracker!$H:$H,Money_tracker!$D:$D,$A4,Money_tracker!$C:$C,"Outcome",Money_tracker!$F:$F,"IDR",Money_tracker!$C:$C,"<>Pindah",Money_tracker!$E:$E,"<>Transfer") -> 0
A5: Mandiri | B5: =SUMIFS(Money_tracker!$H:$H,Money_tracker!$D:$D,$A5,Money_tracker!$C:$C,"Income",Money_tracker!$F:$F,"IDR",Money_tracker!$C:$C,"<>Pindah",Money_tracker!$E:$E,"<>Transfer",Money_tracker!$C:$C,"<>Sisa saldo")+SUMIFS(Money_tracker!$H:$H,Money_tracker!$D:$D,$A5,Money_tracker!$C:$C,"Sisa saldo",Money_tracker!$F:$F,"IDR",Money_tracker!$E:$E,"Sisa saldo")-SUMIFS(Money_tracker!$H:$H,Money_tracker!$D:$D,$A5,Money_tracker!$C:$C,"Outcome",Money_tracker!$F:$F,"IDR",Money_tracker!$C:$C,"<>Pindah",Money_tracker!$E:$E,"<>Transfer") -> 21550
A6: Seabank | B6: =SUMIFS(Money_tracker!$H:$H,Money_tracker!$D:$D,$A6,Money_tracker!$C:$C,"Income",Money_tracker!$F:$F,"IDR",Money_tracker!$C:$C,"<>Pindah",Money_tracker!$E:$E,"<>Transfer",Money_tracker!$C:$C,"<>Sisa saldo")+SUMIFS(Money_tracker!$H:$H,Money_tracker!$D:$D,$A6,Money_tracker!$C:$C,"Sisa saldo",Money_tracker!$F:$F,"IDR",Money_tracker!$E:$E,"Sisa saldo")-SUMIFS(Money_tracker!$H:$H,Money_tracker!$D:$D,$A6,Money_tracker!$C:$C,"Outcome",Money_tracker!$F:$F,"IDR",Money_tracker!$C:$C,"<>Pindah",Money_tracker!$E:$E,"<>Transfer") -> 3284019
A7: Grand Total | B7: =SUM(B3:B6) -> 3498267 | E7: =COUNTIFS(Money_tracker!$D:$D,$A6,Money_tracker!$F:$F,"IDR") -> 10
A9: USD ASSETS
A10: Item | B10: USD | C10: Presentase
A11: Jenius | B11: =SUMIFS(Money_tracker!$H:$H,Money_tracker!$D:$D,$A11,Money_tracker!$C:$C,"Income",Money_tracker!$F:$F,"USD",Money_tracker!$C:$C,"<>Pindah",Money_tracker!$E:$E,"<>Transfer",Money_tracker!$C:$C,"<>Sisa saldo")+SUMIFS(Money_tracker!$H:$H,Money_tracker!$D:$D,$A11,Money_tracker!$C:$C,"Sisa saldo",Money_tracker!$F:$F,"USD",Money_tracker!$E:$E,"Sisa saldo")-SUMIFS(Money_tracker!$H:$H,Money_tracker!$D:$D,$A11,Money_tracker!$C:$C,"Outcome",Money_tracker!$F:$F,"USD",Money_tracker!$C:$C,"<>Pindah",Money_tracker!$E:$E,"<>Transfer") -> 705
A12: BCA Vallas | B12: =SUMIFS(Money_tracker!$H:$H,Money_tracker!$D:$D,$A12,Money_tracker!$C:$C,"Income",Money_tracker!$F:$F,"USD",Money_tracker!$C:$C,"<>Pindah",Money_tracker!$E:$E,"<>Transfer",Money_tracker!$C:$C,"<>Sisa saldo")+SUMIFS(Money_tracker!$H:$H,Money_tracker!$D:$D,$A12,Money_tracker!$C:$C,"Sisa saldo",Money_tracker!$F:$F,"USD",Money_tracker!$E:$E,"Sisa saldo")-SUMIFS(Money_tracker!$H:$H,Money_tracker!$D:$D,$A12,Money_tracker!$C:$C,"Outcome",Money_tracker!$F:$F,"USD",Money_tracker!$C:$C,"<>Pindah",Money_tracker!$E:$E,"<>Transfer") -> 5
A13: Grand Total | B13: =SUM(B11:B12) -> 710
A15: INVESTMENT ASSETS
A16: Item | B16: Quantity | C16: Total | D16: Presentase
A17: Gold | B17: 3 | C17: =G2*B17 -> 7980000
A18: Saham | C18: 2000000
A19: Grand Total | B19: =SUM(C17:C18) -> 9980000

Sheet List
A1: Metode | C1: Jenis | E1: Mata Uang | G1: Outcome List | I1: Income List
A2: Shopeepay | C2: Pindah | E2: IDR | G2: Makan | I2: Gaji
A3: Gopay | C3: Sisa saldo | E3: USD | G3: Minuman | I3: Bonus
A4: Seabank | C4: Income | G4: Sedekah | I4: Sisa
A5: BCA | C5: Outcome | G5: Fashion | I5: Other
A6: Mandiri | G6: Investasi
A7: Jenius | G7: Sisa saldo
A8: BCA Vallas | G8: Transportasi
A9: Investasi | G9: Other
A10: BCA Vallas | G10: Rokok
A11: Cash | G11: Transfer
G12: Kesehatan
